README.md
bng.py
setup.py
bng.egg-info/PKG-INFO
bng.egg-info/SOURCES.txt
bng.egg-info/dependency_links.txt
bng.egg-info/top_level.txt