Metadata-Version: 2.1
Name: bng
Version: 1.0.2
Summary: Convert between BNG grid refs (e.g. NT123456) and OSGB36 (EPSG:27700) coords
Home-page: https://github.com/volcan01010/bng
Author: Dr John A Stevenson
Author-email: johnalexanderstevenson@gmail.com
License: GPLv3.0
Platform: UNKNOWN
Classifier: Programming Language :: Python :: 3
Classifier: Programming Language :: Python :: 2.7
